detect_and_display/__init__.py
detect_and_display/detect_and_display.py
detect_and_display/utils/__init__.py
detect_and_display/utils/detect_and_display_logger.py
detect_and_display/utils/singleton.py
detect_and_display_cli/__init__.py
detect_and_display_cli/commands/__init__.py
detect_and_display_cli/commands/cmd_display.py
detect_and_display_cli/detect_and_display_cli.py
detect_and_display-0.1.1.dist-info/entry_points.txt
detect_and_display-0.1.1.dist-info/WHEEL
detect_and_display-0.1.1.dist-info/METADATA
detect_and_display-0.1.1.dist-info/RECORD
