Metadata-Version: 2.1
Name: detect-and-display
Version: 0.1.1
Summary: 
Author: patricio tula
Author-email: tula.patricio@gmail.com
Requires-Python: >=3.8,<4.0
Classifier: Programming Language :: Python :: 3
Classifier: Programming Language :: Python :: 3.8
Classifier: Programming Language :: Python :: 3.9
Requires-Dist: click (>=8.0.1,<9.0.0)
